certbot_dns_nodeup/__init__.py
certbot_dns_nodeup/_internal/__init__.py
certbot_dns_nodeup/_internal/dns_nodeup.py
certbot_dns_nodeup-1.2.1.dist-info/METADATA
certbot_dns_nodeup-1.2.1.dist-info/WHEEL
certbot_dns_nodeup-1.2.1.dist-info/entry_points.txt
certbot_dns_nodeup-1.2.1.dist-info/top_level.txt
certbot_dns_nodeup-1.2.1.dist-info/RECORD
